chibi/__init__.py
chibi/chibi.py
chibi_store_wallet-1.0.6.dist-info/LICENSE
chibi_store_wallet-1.0.6.dist-info/METADATA
chibi_store_wallet-1.0.6.dist-info/WHEEL
chibi_store_wallet-1.0.6.dist-info/top_level.txt
chibi_store_wallet-1.0.6.dist-info/RECORD
