Metadata-Version: 2.1
Name: chibi_store_wallet
Version: 1.0.6
Summary: Redeem TrueMoney gift via Python
Home-page: https://github.com/yourusername/chibi-redeem
Author: PARK
Author-email: PARK <parkontop07@gmail.com>
License: MIT
Project-URL: Homepage, https://github.com/yourusername/chibi-redeem
Keywords: truemoney,redeem,wallet,gift,python
Classifier: Programming Language :: Python :: 3
Classifier: Operating System :: OS Independent
Requires-Python: >=3.6
License-File: LICENSE
Requires-Dist: requests
